{
  "27": {
    "1-1": "네 부위의 뼈 개수를 모두 합친 총합은 150보다 크고 200보다 작다.",
    "1-2": "네 부위 중 뼈 개수가 짝수인 부위의 개수와 홀수인 부위의 개수는 같다.",
    "1-3": "가장 개수가 적은 부위는 20대(20~29개)에 속한다.",
    "1-4": "개수가 40개 이상인 부위는 정확히 두 곳이다.",
    "1-5": "머리뼈는 꼬리뼈보다 개수가 많다.",
    "1-6": "꼬리뼈는 몸통뼈보다 개수가 많다.",
    "1-7": "몸통뼈는 다리뼈보다 개수가 많다.",
    "1-8": "모든 부위의 뼈 개수는 서로 다른 자연수이다.",
    "1-9": "머리뼈의 개수를 5로 나누면 나머지가 1이다.",
    "1-10": "가장 개수가 많은 부위와 가장 개수가 적은 부위의 차이는 25보다 크다.",
    "1-11": "몸통뼈는 3의 배수이다.",
    "1-12": "전체 뼈 조각 수(총합)의 일의 자리는 0이다.",
    "1-13": "50개를 초과하는 부위가 적어도 하나 존재한다.",
    "1-14": "30개 미만인 부위는 정확히 한 곳이다.",
    "1-15": "비교 감정권: 원하는 두 부위를 골라 어느 쪽이 더 많은지 디렉터에게 1회 질문할 수 있다.",
    "1-16": "범위 감정권: 원하는 부위 하나를 골라 10단위 범위(예: 30대, 40대 등)를 디렉터에게 1회 질문할 수 있다.",
    "2-1": "머리뼈와 다리뼈의 차이는 어떤 자연수의 세제곱 수와 같다.",
    "2-2": "꼬리뼈와 몸통뼈의 차이는 소수(Prime number)이다.",
    "2-3": "머리뼈와 꼬리뼈의 차이 역시 소수(Prime number)이다.",
    "2-4": "머리뼈와 몸통뼈의 합은 45의 배수이다.",
    "2-5": "다리뼈에 2배를 한 값은 꼬리뼈보다 크다.",
    "2-6": "몸통뼈와 다리뼈의 차이는 10보다 크고 20보다 작다.",
    "2-7": "네 부위 중 개수가 소수(Prime number)인 부위는 단 하나도 없다.",
    "2-8": "꼬리뼈는 어떤 소수(Prime number)의 배수이다.",
    "2-9": "다리뼈는 4의 배수이다.",
    "2-10": "가장 개수가 많은 두 부위의 합은 90보다 크고 100보다 작다.",
    "2-11": "어떤 부위도 다른 부위의 개수와 정확히 2배 차이가 나지 않는다.",
    "2-12": "머리뼈와 몸통뼈는 뼈 개수 순위상 인접하지 않는다.",
    "2-13": "꼬리뼈와 다리뼈의 합은 전체 총합의 절반보다 작다.",
    "2-14": "몸통뼈의 일의 자리 숫자는 9이다.",
    "2-15": "순위 감정권: 원하는 부위 하나를 골라 그 부위가 뼈 개수 순위로 몇 등인지 디렉터에게 1회 질문할 수 있다.",
    "2-16": "비교 감정권: 원하는 두 부위를 골라 어느 쪽이 더 많은지 디렉터에게 1회 질문할 수 있다.",
    "3-1": "머리뼈와 꼬리뼈의 합은 소수(Prime number)이다.",
    "3-2": "몸통뼈와 다리뼈의 합은 9의 배수이다.",
    "3-3": "머리뼈와 다리뼈의 합은 25의 배수이다.",
    "3-4": "꼬리뼈에서 다리뼈를 뺀 값의 절댓값은 짝수이다.",
    "3-5": "가장 많은 세 부위의 합은 130을 초과한다.",
    "3-6": "몸통뼈에서 다리뼈를 뺀 값은 3의 배수이다.",
    "3-7": "머리뼈와 몸통뼈의 최대공약수(GCD)는 3이다.",
    "3-8": "꼬리뼈와 다리뼈의 최대공약수(GCD)는 2이다.",
    "3-9": "네 개의 부위 중 정확히 세 개의 부위가 3의 배수이다.",
    "3-10": "꼬리뼈와 몸통뼈의 합은 80보다 크고 100보다 작다.",
    "3-11": "다리뼈를 제외한 나머지 세 부위의 합은 8의 배수이다.",
    "3-12": "전체 총합을 다리뼈의 개수로 나누면 나머지가 16이다.",
    "3-13": "꼬리뼈와 몸통뼈의 합은 5의 배수이다.",
    "3-14": "어떤 두 부위의 합도 전체 총합의 3분의 2를 넘지 못한다.",
    "3-15": "합산 감정권: 원하는 두 부위를 골라 두 부위의 합이 80 이상인지 미만인지 디렉터에게 1회 질문할 수 있다.",
    "3-16": "차이 감정권: 원하는 두 부위를 골라 두 부위의 차이가 10 이상인지 미만인지 디렉터에게 1회 질문할 수 있다.",
    "4-1": "네 부위의 전체 평균은 35보다 크고 45보다 작다.",
    "4-2": "몸통뼈는 전체 평균과 개수가 가장 가까운 부위이다.",
    "4-3": "다리뼈는 전체 평균에서 개수가 가장 멀리 떨어진 부위이다.",
    "4-4": "머리뼈와 꼬리뼈는 모두 평균보다 개수가 많다.",
    "4-5": "몸통뼈와 다리뼈는 모두 평균보다 개수가 적다.",
    "4-6": "네 부위의 뼈 개수를 오름차순으로 정렬했을 때, 중앙값(Median)은 42.5이다.",
    "4-7": "머리뼈와 다리뼈의 차이는 몸통뼈와 꼬리뼈의 차이보다 20만큼 더 크다.",
    "4-8": "명제: 만약 꼬리뼈가 짝수라면, 머리뼈는 홀수이다.",
    "4-9": "진실의 문: 다음 세 문장 중 정확히 두 문장만 참이다. 'H는 50을 초과한다.', 'B는 40 이상이다.', 'L은 25 미만이다.'",
    "4-10": "머리뼈와 몸통뼈의 차이는 10보다 크다.",
    "4-11": "꼬리뼈와 다리뼈의 차이와, 다리뼈 개수 자체의 차이는 2이다.",
    "4-12": "머리뼈와 꼬리뼈의 차이는 두 소수(Prime number)의 합과 같다.",
    "4-13": "몸통뼈의 각 자리 숫자의 합은 12이다.",
    "4-14": "꼬리뼈의 각 자리 숫자의 합은 10이다.",
    "4-15": "배수 감정권: 원하는 부위 하나와 2~5 사이의 숫자 하나를 골라, 해당 부위가 그 숫자의 배수인지 디렉터에게 1회 질문할 수 있다.",
    "4-16": "소수 감정권: 원하는 부위 두 개를 골라 두 부위의 차이가 소수인지 디렉터에게 1회 질문할 수 있다.",
    "5-1": "명제: 만약 머리뼈와 몸통뼈의 합이 90이라면, 꼬리뼈와 다리뼈의 합은 70이다.",
    "5-2": "머리뼈에 3을 곱한 값은 150보다 크다.",
    "5-3": "몸통뼈에 4를 곱한 값은 전체 총합보다 작다.",
    "5-4": "네 부위 중 십의 자리 숫자가 4인 부위는 정확히 한 곳이다.",
    "5-5": "다리뼈의 십의 자리와 일의 자리를 더하면 3의 배수이다.",
    "5-6": "머리뼈의 십의 자리와 일의 자리를 곱하면 5의 배수이다.",
    "5-7": "모든 부위의 일의 자리는 서로 다른 숫자이다.",
    "5-8": "모든 부위의 일의 자리 숫자를 합하면 20이다.",
    "5-9": "가장 작은 부위에 15를 더하면 두 번째로 작은 부위의 개수가 된다.",
    "5-10": "가장 큰 부위에서 5를 빼면 두 번째로 큰 부위의 개수가 된다.",
    "5-11": "전체 총합은 꼬리뼈와 몸통뼈 차이의 20배보다 크다.",
    "5-12": "머리뼈의 일의 자리는 홀수이다.",
    "5-13": "몸통뼈의 십의 자리는 홀수이다.",
    "5-14": "어떤 부위도 60을 넘지 않는다.",
    "5-15": "평균 감정권: 원하는 부위 하나를 골라 전체 평균보다 큰지 작은지 디렉터에게 1회 질문할 수 있다.",
    "5-16": "진실 감정권: 임의의 명제 2개를 만들어 디렉터에게 질문하면, 디렉터는 둘 중 몇 개가 참인지 알려준다.",
    "6-1": "머리뼈는 10보다 크고 20보다 작은 소수의 배수이다.",
    "6-2": "몸통뼈는 10보다 크고 20보다 작은 소수의 배수이다.",
    "6-3": "꼬리뼈는 20보다 큰 소수의 배수이다.",
    "6-4": "다리뼈는 6의 배수이다.",
    "6-5": "머리뼈와 몸통뼈의 합은 전체 총합의 절반보다 10만큼 더 크다.",
    "6-6": "다리뼈를 제곱하면 400과 800 사이의 수이다.",
    "6-7": "몸통뼈와 꼬리뼈의 차이는 한 자리 수 소수(Prime number)이다.",
    "6-8": "네 부위의 뼈 개수를 오름차순으로 나열할 때, 인접한 부위 간의 차이는 각각 15, 7, 5이다.",
    "6-9": "머리뼈와 다리뼈를 합한 값의 일의 자리와 십의 자리의 합은 12이다.",
    "6-10": "꼬리뼈와 몸통뼈를 합한 값의 일의 자리와 십의 자리의 합은 13이다.",
    "6-11": "몸통뼈를 다리뼈로 나눈 몫은 1이다.",
    "6-12": "가장 개수가 많은 두 부위의 합은, 가장 개수가 적은 두 부위의 합보다 34만큼 더 크다.",
    "6-13": "머리뼈의 일의 자리는 나머지 뼈의 일의 자리 숫자보다 작다",
    "6-14": "모든 부위의 십의 자리 숫자를 합하면 14이다.",
    "6-15": "최종 감정권: 원하는 부위 하나를 골라 디렉터에게 정확한 개수의 '일의 자리'가 홀수인지 짝수인지 1회 질문할 수 있다.",
    "6-16": "최종 감정권: 원하는 부위 하나를 골라 디렉터에게 정확한 개수의 '십의 자리'가 짝수인지 홀수인지 1회 질문할 수 있다."
  },
  "28": {
    "1-1": "네 부위의 뼈 개수를 모두 합친 총합은 150보다 크고 200보다 작다.",
    "1-2": "네 부위 중 뼈 개수가 짝수인 부위의 개수와 홀수인 부위의 개수는 같다.",
    "1-3": "가장 개수가 적은 부위는 20대(20~29개)에 속한다.",
    "1-4": "개수가 40개 이상인 부위는 정확히 두 곳이다.",
    "1-5": "꼬리뼈는 다리뼈보다 개수가 많다.",
    "1-6": "다리뼈는 몸통뼈보다 개수가 많다.",
    "1-7": "몸통뼈는 머리뼈보다 개수가 많다.",
    "1-8": "모든 부위의 뼈 개수는 서로 다른 자연수이다.",
    "1-9": "몸통뼈의 개수를 5로 나누면 나머지가 2이다.",
    "1-10": "가장 개수가 많은 부위와 가장 개수가 적은 부위의 차이는 25보다 크다.",
    "1-11": "머리뼈는 4의 배수이다.",
    "1-12": "전체 뼈 조각 수(총합)의 일의 자리는 0이다.",
    "1-13": "50개를 초과하는 부위가 적어도 하나 존재한다.",
    "1-14": "30개 미만인 부위는 정확히 한 곳이다.",
    "1-15": "비교 감정권: 원하는 두 부위를 골라 어느 쪽이 더 많은지 디렉터에게 1회 질문할 수 있다.",
    "1-16": "범위 감정권: 원하는 부위 하나를 골라 10단위 범위(예: 30대, 40대 등)를 디렉터에게 1회 질문할 수 있다.",
    "2-1": "꼬리뼈와 다리뼈의 차이는 10의 배수이다.",
    "2-2": "다리뼈와 몸통뼈의 차이는 소수(Prime number)이다.",
    "2-3": "꼬리뼈와 몸통뼈의 차이는 어떤 자연수의 세제곱 수와 같다.",
    "2-4": "머리뼈와 꼬리뼈의 합은 소수(Prime number)이다.",
    "2-5": "몸통뼈에 2배를 한 값은 꼬리뼈보다 크다.",
    "2-6": "몸통뼈와 머리뼈의 차이는 10보다 크고 20보다 작다.",
    "2-7": "네 부위 중 개수가 소수(Prime number)인 부위는 단 하나 존재한다.",
    "2-8": "다리뼈는 7의 배수이다.",
    "2-9": "몸통뼈는 8의 배수이다.",
    "2-10": "가장 개수가 많은 두 부위의 합은 90보다 크고 110보다 작다.",
    "2-11": "어떤 부위도 다른 부위의 개수와 정확히 2배 차이가 나지 않는다.",
    "2-12": "꼬리뼈와 몸통뼈는 뼈 개수 순위상 인접하지 않는다.",
    "2-13": "몸통뼈와 머리뼈의 합은 전체 총합의 절반보다 작다.",
    "2-14": "머리뼈의 일의 자리 숫자는 0이다.",
    "2-15": "순위 감정권: 원하는 부위 하나를 골라 그 부위가 뼈 개수 순위로 몇 등인지 디렉터에게 1회 질문할 수 있다.",
    "2-16": "비교 감정권: 원하는 두 부위를 골라 어느 쪽이 더 많은지 디렉터에게 1회 질문할 수 있다.",
    "3-1": "꼬리뼈와 다리뼈의 합은 9의 배수이다.",
    "3-2": "몸통뼈와 머리뼈의 합은 4의 배수이다.",
    "3-3": "꼬리뼈와 몸통뼈의 합은 7의 배수이다.",
    "3-4": "다리뼈와 몸통뼈의 차이는 홀수이다.",
    "3-5": "가장 많은 세 부위의 합은 130을 초과한다.",
    "3-6": "다리뼈와 머리뼈의 차이는 소수(Prime number)이다.",
    "3-7": "머리뼈와 몸통뼈의 최대공약수(GCD)는 4이다.",
    "3-8": "꼬리뼈와 몸통뼈의 최대공약수(GCD)는 1이다.",
    "3-9": "네 개의 부위 중 3의 배수인 부위는 단 하나도 없다.",
    "3-10": "다리뼈와 몸통뼈의 합은 80보다 크고 90보다 작다.",
    "3-11": "머리뼈를 제외한 나머지 세 부위의 합은 10의 배수이다.",
    "3-12": "전체 총합을 다리뼈의 개수로 나누면 나머지가 13이다.",
    "3-13": "꼬리뼈와 머리뼈의 합은 100보다 작다.",
    "3-14": "가장 개수가 많은 두 부위의 합은 전체 총합의 3분의 2보다 크다.",
    "3-15": "합산 감정권: 원하는 두 부위를 골라 두 부위의 합이 80 이상인지 미만인지 디렉터에게 1회 질문할 수 있다.",
    "3-16": "차이 감정권: 원하는 두 부위를 골라 두 부위의 차이가 10 이상인지 미만인지 디렉터에게 1회 질문할 수 있다.",
    "4-1": "네 부위의 전체 평균은 35보다 크고 45보다 작다.",
    "4-2": "몸통뼈는 전체 평균과 개수가 가장 가까운 부위이다.",
    "4-3": "머리뼈는 전체 평균에서 개수가 가장 멀리 떨어진 부위이다.",
    "4-4": "다리뼈와 꼬리뼈는 모두 평균보다 개수가 많다.",
    "4-5": "머리뼈와 몸통뼈는 모두 평균보다 개수가 적다.",
    "4-6": "네 부위의 뼈 개수를 오름차순으로 정렬했을 때, 중앙값(Median)은 40.5이다.",
    "4-7": "다리뼈와 몸통뼈의 차이는 꼬리뼈와 다리뼈의 차이보다 7만큼 더 크다.",
    "4-8": "명제: 만약 다리뼈가 짝수라면, 머리뼈는 홀수이다.",
    "4-9": "진실의 문: 다음 세 문장 중 정확히 두 문장만 참이다. '꼬리뼈는 50을 초과한다.', '다리뼈는 40 이상이다.', '몸통뼈는 25 미만이다.'",
    "4-10": "다리뼈와 머리뼈의 차이는 20보다 크다.",
    "4-11": "꼬리뼈와 몸통뼈의 차이와 다리뼈와 머리뼈의 차이는 2만큼 차이난다.",
    "4-12": "다리뼈와 몸통뼈의 차이는 소수(Prime number)이다.",
    "4-13": "몸통뼈의 각 자리 숫자의 합은 5이다.",
    "4-14": "꼬리뼈의 각 자리 숫자의 합은 14이다.",
    "4-15": "배수 감정권: 원하는 부위 하나와 2~5 사이의 숫자 하나를 골라, 해당 부위가 그 숫자의 배수인지 디렉터에게 1회 질문할 수 있다.",
    "4-16": "소수 감정권: 원하는 부위 두 개를 골라 두 부위의 차이가 소수인지 디렉터에게 1회 질문할 수 있다.",
    "5-1": "명제: 만약 다리뼈와 몸통뼈의 합이 81이라면, 꼬리뼈와 머리뼈의 차이는 39이다.",
    "5-2": "머리뼈에 4를 곱한 값은 100보다 작다.",
    "5-3": "다리뼈에 3을 곱한 값은 전체 총합보다 작다.",
    "5-4": "네 부위 중 십의 자리 숫자가 4인 부위는 정확히 한 곳이다.",
    "5-5": "다리뼈의 일의 자리에서 십의 자리를 빼면 5이다.",
    "5-6": "몸통뼈의 십의 자리와 일의 자리를 곱하면 6이다.",
    "5-7": "일의 자리 숫자가 같은 부위가 정확히 두 곳 존재한다.",
    "5-8": "모든 부위의 일의 자리 숫자를 합하면 20이다.",
    "5-9": "가장 작은 부위에 12를 더하면 두 번째로 작은 부위의 개수가 된다.",
    "5-10": "가장 큰 부위에서 10을 빼면 두 번째로 큰 부위의 개수가 된다.",
    "5-11": "전체 총합은 꼬리뼈와 몸통뼈 차이의 5배보다 크다.",
    "5-12": "다리뼈의 일의 자리는 홀수이다.",
    "5-13": "꼬리뼈의 십의 자리는 홀수이다.",
    "5-14": "어떤 부위도 60을 넘지 않는다.",
    "5-15": "평균 감정권: 원하는 부위 하나를 골라 전체 평균보다 큰지 작은지 디렉터에게 1회 질문할 수 있다.",
    "5-16": "진실 감정권: 임의의 명제 2개를 만들어 디렉터에게 질문하면, 디렉터는 둘 중 몇 개가 참인지 알려준다.",
    "6-1": "다리뼈는 어떤 홀수의 제곱수이다.",
    "6-2": "머리뼈는 5의 배수이다.",
    "6-3": "꼬리뼈는 소수(Prime number)이다.",
    "6-4": "몸통뼈는 8의 배수이다.",
    "6-5": "다리뼈와 몸통뼈의 합은 전체 총합의 절반보다 1만큼 더 크다.",
    "6-6": "몸통뼈를 제곱하면 1000과 1200 사이의 수이다.",
    "6-7": "다리뼈와 몸통뼈의 차이는 10보다 큰 소수(Prime number)이다.",
    "6-8": "네 부위의 뼈 개수를 오름차순으로 나열할 때, 인접한 부위 간의 차이는 각각 12, 17, 10이다.",
    "6-9": "다리뼈와 몸통뼈를 합한 값의 일의 자리와 십의 자리의 합은 9이다.",
    "6-10": "머리뼈와 몸통뼈를 합한 값의 일의 자리와 십의 자리의 합은 7이다.",
    "6-11": "꼬리뼈를 머리뼈로 나누었을 때 몫은 2이다.",
    "6-12": "가장 개수가 많은 두 부위의 합은, 가장 개수가 적은 두 부위의 합보다 56만큼 더 크다.",
    "6-13": "다리뼈의 일의 자리와 꼬리뼈의 일의 자리는 같은 숫자이다.",
    "6-14": "모든 부위의 십의 자리 숫자를 합하면 14이다.",
    "6-15": "최종 감정권: 원하는 부위 하나를 골라 디렉터에게 정확한 개수의 '일의 자리'가 홀수인지 짝수인지 1회 질문할 수 있다.",
    "6-16": "최종 감정권: 원하는 부위 하나를 골라 디렉터에게 정확한 개수의 '십의 자리'가 짝수인지 홀수인지 1회 질문할 수 있다."
  },
  "29": {
    "1-1": "네 부위의 뼈 개수를 모두 합친 총합은 150보다 크고 200보다 작다.",
    "1-2": "네 부위 중 뼈 개수가 짝수인 부위의 개수와 홀수인 부위의 개수는 같다.",
    "1-3": "가장 개수가 적은 부위는 20대(20~29개)에 속한다.",
    "1-4": "개수가 40개 이상인 부위는 정확히 두 곳이다.",
    "1-5": "다리뼈는 몸통뼈보다 개수가 많다.",
    "1-6": "몸통뼈는 머리뼈보다 개수가 많다.",
    "1-7": "머리뼈는 꼬리뼈보다 개수가 많다.",
    "1-8": "모든 부위의 뼈 개수는 서로 다른 자연수이다.",
    "1-9": "머리뼈의 개수를 7로 나누면 나머지가 2이다.",
    "1-10": "가장 개수가 많은 부위와 가장 개수가 적은 부위의 차이는 30보다 크다.",
    "1-11": "머리뼈는 5의 배수이다.",
    "1-12": "전체 뼈 조각 수(총합)의 일의 자리는 0이다.",
    "1-13": "50개를 초과하는 부위는 단 하나 존재한다.",
    "1-14": "30개 미만인 부위는 정확히 한 곳이다.",
    "1-15": "비교 감정권: 원하는 두 부위를 골라 어느 쪽이 더 많은지 디렉터에게 1회 질문할 수 있다.",
    "1-16": "범위 감정권: 원하는 부위 하나를 골라 10단위 범위(예: 30대, 40대 등)를 디렉터에게 1회 질문할 수 있다.",
    "2-1": "꼬리뼈와 다리뼈의 차이는 짝수이다.",
    "2-2": "다리뼈와 몸통뼈의 차이는 소수(Prime number)이다.",
    "2-3": "몸통뼈와 꼬리뼈의 차이는 3의 배수이다.",
    "2-4": "머리뼈와 꼬리뼈의 합은 5의 배수이다.",
    "2-5": "몸통뼈에 2배를 한 값은 다리뼈보다 크다.",
    "2-6": "다리뼈와 몸통뼈의 차이는 10보다 크고 20보다 작다.",
    "2-7": "네 부위 중 개수가 소수(Prime number)인 부위는 단 하나 존재한다.",
    "2-8": "꼬리뼈는 5의 배수이다.",
    "2-9": "몸통뼈는 2의 배수이다.",
    "2-10": "가장 개수가 많은 두 부위의 합은 100보다 크고 110보다 작다.",
    "2-11": "어떤 부위도 다른 부위의 개수와 정확히 2배 차이가 나지 않는다.",
    "2-12": "머리뼈와 다리뼈는 뼈 개수 순위상 인접하지 않는다.",
    "2-13": "몸통뼈와 머리뼈의 합은 전체 총합의 절반보다 작다.",
    "2-14": "다리뼈의 일의 자리 숫자는 9이다.",
    "2-15": "순위 감정권: 원하는 부위 하나를 골라 그 부위가 뼈 개수 순위로 몇 등인지 디렉터에게 1회 질문할 수 있다.",
    "2-16": "비교 감정권: 원하는 두 부위를 골라 어느 쪽이 더 많은지 디렉터에게 1회 질문할 수 있다.",
    "3-1": "꼬리뼈와 다리뼈의 합은 7의 배수이다.",
    "3-2": "몸통뼈와 머리뼈의 합은 4의 배수이다.",
    "3-3": "꼬리뼈와 몸통뼈의 합은 70보다 크고 80보다 작다.",
    "3-4": "다리뼈와 몸통뼈의 차이는 홀수이다.",
    "3-5": "가장 많은 세 부위의 합은 130을 초과한다.",
    "3-6": "다리뼈와 머리뼈의 차이는 소수(Prime number)이다.",
    "3-7": "머리뼈와 몸통뼈의 최대공약수(GCD)는 2이다.",
    "3-8": "꼬리뼈와 머리뼈의 최대공약수(GCD)는 5이다.",
    "3-9": "네 개의 부위 중 3의 배수인 부위는 단 하나 존재한다.",
    "3-10": "머리뼈와 꼬리뼈의 합은 50보다 크고 60보다 작다.",
    "3-11": "머리뼈를 제외한 나머지 세 부위의 합은 10의 배수이다.",
    "3-12": "전체 총합을 다리뼈의 개수로 나누면 나머지가 42이다.",
    "3-13": "꼬리뼈와 머리뼈의 합은 60보다 작다.",
    "3-14": "가장 개수가 많은 두 부위의 합은 전체 총합의 3분의 2보다 작다.",
    "3-15": "합산 감정권: 원하는 두 부위를 골라 두 부위의 합이 80 이상인지 미만인지 디렉터에게 1회 질문할 수 있다.",
    "3-16": "차이 감정권: 원하는 두 부위를 골라 두 부위의 차이가 10 이상인지 미만인지 디렉터에게 1회 질문할 수 있다.",
    "4-1": "네 부위의 전체 평균은 35보다 크고 45보다 작다.",
    "4-2": "몸통뼈는 전체 평균과 개수가 가장 가까운 부위이다.",
    "4-3": "다리뼈는 전체 평균에서 개수가 가장 멀리 떨어진 부위이다.",
    "4-4": "몸통뼈와 다리뼈는 모두 평균보다 개수가 많다.",
    "4-5": "머리뼈와 꼬리뼈는 모두 평균보다 개수가 적다.",
    "4-6": "네 부위의 뼈 개수를 오름차순으로 정렬했을 때, 중앙값(Median)은 38이다.",
    "4-7": "다리뼈와 몸통뼈의 차이는 꼬리뼈와 머리뼈의 차이보다 8만큼 더 크다.",
    "4-8": "명제: 만약 다리뼈가 짝수라면, 머리뼈는 홀수이다.",
    "4-9": "진실의 문: 다음 세 문장 중 정확히 두 문장만 참이다. '다리뼈는 50을 초과한다.', '머리뼈는 30 이상이다.', '몸통뼈는 40 미만이다.'",
    "4-10": "다리뼈와 머리뼈의 차이는 20보다 크다.",
    "4-11": "몸통뼈와 꼬리뼈의 차이와 머리뼈와 꼬리뼈의 차이는 16만큼 차이난다.",
    "4-12": "다리뼈와 몸통뼈의 차이는 10보다 큰 소수(Prime number)이다.",
    "4-13": "몸통뼈의 각 자리 숫자의 합은 10이다.",
    "4-14": "꼬리뼈의 각 자리 숫자의 합은 7이다.",
    "4-15": "배수 감정권: 원하는 부위 하나와 2~6 사이의 숫자 하나를 골라, 해당 부위가 그 숫자의 배수인지 디렉터에게 1회 질문할 수 있다.",
    "4-16": "소수 감정권: 원하는 부위 두 개를 골라 두 부위의 차이가 소수인지 디렉터에게 1회 질문할 수 있다.",
    "5-1": "명제: 만약 다리뼈와 몸통뼈의 합이 105라면, 꼬리뼈와 머리뼈의 차이는 5이다.",
    "5-2": "머리뼈에 4를 곱한 값은 100보다 크다.",
    "5-3": "다리뼈에 3을 곱한 값은 전체 총합보다 크다.",
    "5-4": "네 부위 중 십의 자리 숫자가 4인 부위는 정확히 한 곳이다.",
    "5-5": "꼬리뼈의 일의 자리에서 십의 자리를 빼면 3이다.",
    "5-6": "몸통뼈의 십의 자리와 일의 자리를 곱하면 24이다.",
    "5-7": "모든 부위의 일의 자리는 서로 다른 숫자이다.",
    "5-8": "모든 부위의 일의 자리 숫자를 합하면 20이다.",
    "5-9": "가장 작은 부위에 5를 더하면 두 번째로 작은 부위의 개수가 된다.",
    "5-10": "가장 큰 부위에서 13을 빼면 두 번째로 큰 부위의 개수가 된다.",
    "5-11": "전체 총합은 꼬리뼈와 머리뼈 차이의 30배보다 크다.",
    "5-12": "다리뼈의 일의 자리는 홀수이다.",
    "5-13": "꼬리뼈의 십의 자리는 짝수이다.",
    "5-14": "어떤 부위도 60을 넘지 않는다.",
    "5-15": "평균 감정권: 원하는 부위 하나를 골라 전체 평균보다 큰지 작은지 디렉터에게 1회 질문할 수 있다.",
    "5-16": "진실 감정권: 임의의 명제 2개를 만들어 디렉터에게 질문하면, 디렉터는 둘 중 몇 개가 참인지 알려준다.",
    "6-1": "다리뼈는 어떤 수의 제곱수도 아니며 홀수이다.",
    "6-2": "머리뼈는 6의 배수이다.",
    "6-3": "꼬리뼈는 어떤 홀수의 제곱수이다.",
    "6-4": "몸통뼈는 짝수이며 4의 배수가 아니다.",
    "6-5": "다리뼈와 몸통뼈의 합은 전체 총합의 절반보다 25만큼 더 크다.",
    "6-6": "몸통뼈를 제곱하면 2000과 2200 사이의 수이다.",
    "6-7": "다리뼈와 몸통뼈의 차이는 두 자리 수 소수(Prime number)이다.",
    "6-8": "네 부위의 뼈 개수를 오름차순으로 나열할 때, 인접한 부위 간의 차이는 각각 5, 16, 13이다.",
    "6-9": "다리뼈와 몸통뼈를 합한 값의 일의 자리와 십의 자리의 합은 6이다.",
    "6-10": "머리뼈와 몸통뼈를 합한 값의 일의 자리와 십의 자리의 합은 13이다.",
    "6-11": "몸통뼈를 머리뼈로 나누었을 때 몫은 1이다.",
    "6-12": "가장 개수가 많은 두 부위의 합은, 가장 개수가 적은 두 부위의 합보다 50만큼 더 크다.",
    "6-13": "다리뼈의 일의 자리는 가장 큰 한 자리 자연수이다.",
    "6-14": "모든 부위의 십의 자리 숫자를 합하면 14이다.",
    "6-15": "최종 감정권: 원하는 부위 하나를 골라 디렉터에게 정확한 개수의 '일의 자리'가 홀수인지 짝수인지 1회 질문할 수 있다.",
    "6-16": "최종 감정권: 원하는 부위 하나를 골라 디렉터에게 정확한 개수의 '십의 자리'가 짝수인지 홀수인지 1회 질문할 수 있다."
  },
  "30": {
    "1-1": "네 부위의 뼈 개수를 모두 합친 총합은 150보다 크고 200보다 작다.",
    "1-2": "네 부위 중 뼈 개수가 짝수인 부위의 개수와 홀수인 부위의 개수는 같다.",
    "1-3": "가장 개수가 적은 부위는 20대(20~29개)에 속한다.",
    "1-4": "개수가 40개 이상인 부위는 정확히 두 곳이다.",
    "1-5": "몸통뼈는 머리뼈보다 개수가 많다.",
    "1-6": "머리뼈는 꼬리뼈보다 개수가 많다.",
    "1-7": "꼬리뼈는 다리뼈보다 개수가 많다.",
    "1-8": "모든 부위의 뼈 개수는 서로 다른 자연수이다.",
    "1-9": "머리뼈의 개수를 5로 나누면 나머지가 2이다.",
    "1-10": "가장 개수가 많은 부위와 가장 개수가 적은 부위의 차이는 25보다 크다.",
    "1-11": "머리뼈는 6의 배수이다.",
    "1-12": "전체 뼈 조각 수(총합)의 일의 자리는 0이다.",
    "1-13": "50개를 초과하는 부위는 단 하나 존재한다.",
    "1-14": "30개 미만인 부위는 정확히 한 곳이다.",
    "1-15": "비교 감정권: 원하는 두 부위를 골라 어느 쪽이 더 많은지 디렉터에게 1회 질문할 수 있다.",
    "1-16": "범위 감정권: 원하는 부위 하나를 골라 10단위 범위(예: 30대, 40대 등)를 디렉터에게 1회 질문할 수 있다.",
    "2-1": "꼬리뼈와 다리뼈의 차이는 가장 작은 홀수이다.",
    "2-2": "몸통뼈와 머리뼈의 차이는 소수(Prime number)이다.",
    "2-3": "머리뼈와 꼬리뼈의 차이는 4의 배수이다.",
    "2-4": "몸통뼈와 다리뼈의 합은 8의 배수이다.",
    "2-5": "다리뼈에 2배를 한 값은 몸통뼈보다 작다.",
    "2-6": "머리뼈와 다리뼈의 차이는 10보다 크고 20보다 작다.",
    "2-7": "네 부위 중 개수가 소수(Prime number)인 부위는 정확히 두 곳 존재한다.",
    "2-8": "꼬리뼈는 6의 배수이다.",
    "2-9": "머리뼈는 7의 배수이다.",
    "2-10": "가장 개수가 많은 두 부위의 합은 90보다 크고 110보다 작다.",
    "2-11": "어떤 부위도 다른 부위의 개수와 정확히 2배 차이가 나지 않는다.",
    "2-12": "몸통뼈와 꼬리뼈는 뼈 개수 순위상 인접하지 않는다.",
    "2-13": "꼬리뼈와 다리뼈의 합은 전체 총합의 절반보다 작다.",
    "2-14": "몸통뼈의 일의 자리 숫자는 9이다.",
    "2-15": "순위 감정권: 원하는 부위 하나를 골라 그 부위가 뼈 개수 순위로 몇 등인지 디렉터에게 1회 질문할 수 있다.",
    "2-16": "비교 감정권: 원하는 두 부위를 골라 어느 쪽이 더 많은지 디렉터에게 1회 질문할 수 있다.",
    "3-1": "머리뼈와 꼬리뼈의 합은 8의 배수이다.",
    "3-2": "몸통뼈와 다리뼈의 합은 11의 배수이다.",
    "3-3": "머리뼈와 몸통뼈의 합은 100보다 크고 110보다 작다.",
    "3-4": "몸통뼈와 다리뼈의 차이는 10의 배수이다.",
    "3-5": "가장 많은 세 부위의 합은 130을 초과한다.",
    "3-6": "머리뼈와 다리뼈의 차이는 소수(Prime number)이다.",
    "3-7": "머리뼈와 꼬리뼈의 최대공약수(GCD)는 6이다.",
    "3-8": "몸통뼈와 다리뼈의 최대공약수(GCD)는 1이다.",
    "3-9": "네 개의 부위 중 3의 배수인 부위는 정확히 두 곳 존재한다.",
    "3-10": "머리뼈와 다리뼈의 합은 70보다 크고 80보다 작다.",
    "3-11": "다리뼈를 제외한 나머지 세 부위의 합은 홀수이다.",
    "3-12": "전체 총합을 머리뼈의 개수로 나누면 나머지가 34이다.",
    "3-13": "꼬리뼈와 다리뼈의 합은 60보다 작다.",
    "3-14": "가장 개수가 많은 두 부위의 합은 전체 총합의 3분의 2보다 작다.",
    "3-15": "합산 감정권: 원하는 두 부위를 골라 두 부위의 합이 80 이상인지 미만인지 디렉터에게 1회 질문할 수 있다.",
    "3-16": "차이 감정권: 원하는 두 부위를 골라 두 부위의 차이가 10 이상인지 미만인지 디렉터에게 1회 질문할 수 있다.",
    "4-1": "네 부위의 전체 평균은 35보다 크고 45보다 작다.",
    "4-2": "머리뼈는 전체 평균과 개수가 가장 가까운 부위이다.",
    "4-3": "몸통뼈는 전체 평균에서 개수가 가장 멀리 떨어진 부위이다.",
    "4-4": "몸통뼈와 머리뼈는 모두 평균보다 개수가 많다.",
    "4-5": "다리뼈와 꼬리뼈는 모두 평균보다 개수가 적다.",
    "4-6": "네 부위의 뼈 개수를 오름차순으로 정렬했을 때, 중앙값(Median)은 36이다.",
    "4-7": "몸통뼈와 머리뼈의 차이는 꼬리뼈와 다리뼈의 차이보다 16만큼 더 크다.",
    "4-8": "명제: 만약 다리뼈가 짝수라면, 머리뼈는 홀수이다.",
    "4-9": "진실의 문: 다음 세 문장 중 정확히 두 문장만 참이다. '다리뼈는 30 미만이다.', '몸통뼈는 50 미만이다.', '꼬리뼈는 35 미만이다.'",
    "4-10": "몸통뼈의 십의 자리 숫자는 머리뼈의 일의 자리 숫자보다 크다.",
    "4-11": "머리뼈와 꼬리뼈의 차이는 10보다 크고 20보다 작다.",
    "4-12": "다리뼈와 꼬리뼈의 차이는 가장 작은 자연수이다.",
    "4-13": "머리뼈의 각 자리 숫자의 합은 6이다.",
    "4-14": "다리뼈의 각 자리 숫자의 합은 11이다.",
    "4-15": "배수 감정권: 원하는 부위 하나와 2~6 사이의 숫자 하나를 골라, 해당 부위가 그 숫자의 배수인지 디렉터에게 1회 질문할 수 있다.",
    "4-16": "소수 감정권: 원하는 부위 두 개를 골라 두 부위의 차이가 소수인지 디렉터에게 1회 질문할 수 있다.",
    "5-1": "명제: 만약 다리뼈와 꼬리뼈의 합이 59라면, 머리뼈와 몸통뼈의 차이는 17이다.",
    "5-2": "다리뼈에 4를 곱한 값은 100보다 크다.",
    "5-3": "머리뼈에 3을 곱한 값은 전체 총합보다 작다.",
    "5-4": "네 부위 중 십의 자리 숫자가 2인 부위는 정확히 한 곳이다.",
    "5-5": "머리뼈의 십의 자리에서 일의 자리를 빼면 2이다.",
    "5-6": "꼬리뼈의 십의 자리와 일의 자리를 곱하면 0이다.",
    "5-7": "모든 부위의 십의 자리는 서로 다른 숫자이다.",
    "5-8": "모든 부위의 십의 자리 숫자를 합하면 14이다.",
    "5-9": "가장 작은 부위에 13을 더하면 두 번째로 큰 부위의 개수가 된다.",
    "5-10": "가장 큰 부위에서 17을 빼면 두 번째로 큰 부위의 개수가 된다.",
    "5-11": "전체 총합은 다리뼈와 꼬리뼈 차이의 100배보다 크다.",
    "5-12": "다리뼈의 일의 자리는 가장 큰 한 자리 자연수이다.",
    "5-13": "꼬리뼈의 십의 자리는 홀수이다.",
    "5-14": "어떤 부위도 60을 넘지 않는다.",
    "5-15": "평균 감정권: 원하는 부위 하나를 골라 전체 평균보다 큰지 작은지 디렉터에게 1회 질문할 수 있다.",
    "5-16": "진실 감정권: 임의의 명제 2개를 만들어 디렉터에게 질문하면, 디렉터는 둘 중 몇 개가 참인지 알려준다.",
    "6-1": "다리뼈는 20과 30 사이의 소수(Prime number)이다.",
    "6-2": "머리뼈는 6의 배수이며 7의 배수이다.",
    "6-3": "꼬리뼈는 5의 배수이며 6의 배수이다.",
    "6-4": "몸통뼈는 50과 60 사이의 소수(Prime number)이다.",
    "6-5": "다리뼈와 몸통뼈의 합은 전체 총합의 절반보다 8만큼 더 크다.",
    "6-6": "꼬리뼈를 제곱하면 800과 1000 사이의 수이다.",
    "6-7": "몸통뼈와 머리뼈의 차이는 두 자리 수 소수(Prime number)이다.",
    "6-8": "네 부위의 뼈 개수를 오름차순으로 나열할 때, 인접한 부위 간의 차이는 각각 1, 12, 17이다.",
    "6-9": "머리뼈와 꼬리뼈를 합한 값의 일의 자리와 십의 자리의 합은 9이다.",
    "6-10": "다리뼈와 꼬리뼈를 합한 값의 일의 자리와 십의 자리의 합은 14이다.",
    "6-11": "몸통뼈를 머리뼈로 나누었을 때 몫은 1이다.",
    "6-12": "가장 개수가 많은 두 부위의 합은, 가장 개수가 적은 두 부위의 합보다 42만큼 더 크다.",
    "6-13": "꼬리뼈의 일의 자리는 0이다.",
    "6-14": "모든 부위의 일의 자리 숫자를 합하면 20이다.",
    "6-15": "최종 감정권: 원하는 부위 하나를 골라 디렉터에게 정확한 개수의 '일의 자리'가 홀수인지 짝수인지 1회 질문할 수 있다.",
    "6-16": "최종 감정권: 원하는 부위 하나를 골라 디렉터에게 정확한 개수의 '십의 자리'가 짝수인지 홀수인지 1회 질문할 수 있다."
  },
  "31": {
    "1-1": "네 부위의 뼈 개수를 모두 합친 총합은 150보다 크고 200보다 작다.",
    "1-2": "네 부위 중 뼈 개수가 짝수인 부위의 개수와 홀수인 부위의 개수는 같다.",
    "1-3": "가장 개수가 많은 부위는 50대(50~59개)에 속한다.",
    "1-4": "개수가 30개 이상 50개 미만인 부위는 정확히 두 곳이다.",
    "1-5": "머리뼈는 꼬리뼈보다 개수가 많다.",
    "1-6": "꼬리뼈는 다리뼈보다 개수가 많다.",
    "1-7": "다리뼈는 몸통뼈보다 개수가 많다.",
    "1-8": "모든 부위의 뼈 개수는 서로 다른 자연수이다.",
    "1-9": "머리뼈의 개수를 5로 나누면 나머지가 2이다.",
    "1-10": "가장 개수가 많은 부위와 가장 개수가 적은 부위의 차이는 30보다 크다.",
    "1-11": "머리뼈는 3의 배수이다.",
    "1-12": "전체 뼈 조각 수(총합)의 일의 자리는 0이다.",
    "1-13": "50개를 초과하는 부위는 단 하나 존재한다.",
    "1-14": "30개 미만인 부위는 정확히 한 곳이다.",
    "1-15": "비교 감정권: 원하는 두 부위를 골라 어느 쪽이 더 많은지 디렉터에게 1회 질문할 수 있다.",
    "1-16": "범위 감정권: 원하는 부위 하나를 골라 10단위 범위(예: 30대, 40대 등)를 디렉터에게 1회 질문할 수 있다.",
    "2-1": "꼬리뼈와 몸통뼈의 차이는 어떤 자연수의 제곱수이다.",
    "2-2": "다리뼈와 몸통뼈의 차이는 5의 배수이다.",
    "2-3": "머리뼈와 꼬리뼈의 차이는 소수(Prime number)이다.",
    "2-4": "다리뼈와 꼬리뼈의 합은 소수(Prime number)이다.",
    "2-5": "몸통뼈에 2배를 한 값은 다리뼈보다 크다.",
    "2-6": "머리뼈와 다리뼈의 차이는 10보다 크고 20보다 작다.",
    "2-7": "네 부위 중 개수가 소수(Prime number)인 부위는 단 하나도 없다.",
    "2-8": "꼬리뼈는 8의 배수이다.",
    "2-9": "몸통뼈는 6의 배수이다.",
    "2-10": "가장 개수가 많은 두 부위의 합은 90보다 크고 100보다 작다.",
    "2-11": "어떤 부위도 다른 부위의 개수와 정확히 2배 차이가 나지 않는다.",
    "2-12": "머리뼈와 다리뼈는 뼈 개수 순위상 인접하지 않는다.",
    "2-13": "몸통뼈와 다리뼈의 합은 전체 총합의 절반보다 작다.",
    "2-14": "다리뼈의 일의 자리 숫자는 9이다.",
    "2-15": "순위 감정권: 원하는 부위 하나를 골라 그 부위가 뼈 개수 순위로 몇 등인지 디렉터에게 1회 질문할 수 있다.",
    "2-16": "비교 감정권: 원하는 두 부위를 골라 어느 쪽이 더 많은지 디렉터에게 1회 질문할 수 있다.",
    "3-1": "머리뼈와 다리뼈의 합은 8의 배수이다.",
    "3-2": "몸통뼈와 꼬리뼈의 합은 8의 배수이다.",
    "3-3": "꼬리뼈와 다리뼈의 합은 70보다 크고 80보다 작다.",
    "3-4": "머리뼈와 몸통뼈의 차이는 3의 배수이다.",
    "3-5": "가장 많은 세 부위의 합은 130을 초과한다.",
    "3-6": "꼬리뼈와 다리뼈의 차이는 가장 작은 홀수이다.",
    "3-7": "머리뼈와 다리뼈의 최대공약수(GCD)는 3이다.",
    "3-8": "몸통뼈와 꼬리뼈의 최대공약수(GCD)는 8이다.",
    "3-9": "네 개의 부위 중 3의 배수인 부위는 정확히 세 곳 존재한다.",
    "3-10": "몸통뼈와 다리뼈의 합은 60보다 크고 70보다 작다.",
    "3-11": "꼬리뼈를 제외한 나머지 세 부위의 합은 10의 배수이다.",
    "3-12": "전체 총합을 몸통뼈의 개수로 나누면 나머지가 16이다.",
    "3-13": "머리뼈와 꼬리뼈의 합은 소수(Prime number)이다.",
    "3-14": "가장 개수가 많은 두 부위의 합은 전체 총합의 3분의 2보다 작다.",
    "3-15": "합산 감정권: 원하는 두 부위를 골라 두 부위의 합이 80 이상인지 미만인지 디렉터에게 1회 질문할 수 있다.",
    "3-16": "차이 감정권: 원하는 두 부위를 골라 두 부위의 차이가 10 이상인지 미만인지 디렉터에게 1회 질문할 수 있다.",
    "4-1": "네 부위의 전체 평균은 40이다.",
    "4-2": "꼬리뼈는 전체 평균과 개수가 가장 가까운 부위이다.",
    "4-3": "머리뼈는 전체 평균에서 개수가 가장 멀리 떨어진 부위이다.",
    "4-4": "머리뼈는 유일하게 평균보다 개수가 많은 부위이다.",
    "4-5": "몸통뼈와 다리뼈는 모두 평균보다 개수가 적다.",
    "4-6": "네 부위의 뼈 개수를 오름차순으로 정렬했을 때, 중앙값(Median)은 39.5이다.",
    "4-7": "머리뼈와 다리뼈의 차이는 꼬리뼈와 몸통뼈의 차이보다 2만큼 더 크다.",
    "4-8": "명제: 만약 다리뼈가 홀수라면, 꼬리뼈는 짝수이다.",
    "4-9": "진실의 문: 다음 세 문장 중 정확히 두 문장만 참이다. '머리뼈는 50을 초과한다.', '몸통뼈는 30 이상이다.', '다리뼈는 40 미만이다.'",
    "4-10": "몸통뼈의 십의 자리 숫자는 꼬리뼈의 십의 자리 숫자보다 작다.",
    "4-11": "머리뼈와 몸통뼈의 차이는 30보다 크다.",
    "4-12": "꼬리뼈와 다리뼈의 차이는 가장 작은 자연수이다.",
    "4-13": "머리뼈의 각 자리 숫자의 합은 12이다.",
    "4-14": "몸통뼈의 각 자리 숫자의 합은 6이다.",
    "4-15": "배수 감정권: 원하는 부위 하나와 2~6 사이의 숫자 하나를 골라, 해당 부위가 그 숫자의 배수인지 디렉터에게 1회 질문할 수 있다.",
    "4-16": "소수 감정권: 원하는 부위 두 개를 골라 두 부위의 차이가 소수인지 디렉터에게 1회 질문할 수 있다.",
    "5-1": "명제: 만약 꼬리뼈와 몸통뼈의 합이 64라면, 머리뼈와 다리뼈의 차이는 18이다.",
    "5-2": "다리뼈에 4를 곱한 값은 150보다 크다.",
    "5-3": "몸통뼈에 5를 곱한 값은 전체 총합보다 작다.",
    "5-4": "네 부위 중 십의 자리 숫자가 3인 부위는 정확히 한 곳이다.",
    "5-5": "다리뼈의 일의 자리와 십의 자리의 차이는 6이다.",
    "5-6": "꼬리뼈의 십의 자리와 일의 자리를 곱하면 0이다.",
    "5-7": "모든 부위의 십의 자리는 서로 다른 숫자이다.",
    "5-8": "모든 부위의 십의 자리 숫자를 합하면 14이다.",
    "5-9": "가장 개수가 적은 부위와 두 번째로 개수가 적은 부위의 차이는 15이다.",
    "5-10": "가장 개수가 많은 부위와 두 번째로 개수가 많은 부위의 차이는 17이다.",
    "5-11": "전체 총합은 머리뼈와 꼬리뼈 차이의 9배보다 크다.",
    "5-12": "머리뼈의 일의 자리는 소수(Prime number)이다.",
    "5-13": "꼬리뼈의 일의 자리는 0이다.",
    "5-14": "어떤 부위도 60을 넘지 않는다.",
    "5-15": "평균 감정권: 원하는 부위 하나를 골라 전체 평균보다 큰지 작은지 디렉터에게 1회 질문할 수 있다.",
    "5-16": "진실 감정권: 임의의 명제 2개를 만들어 디렉터에게 질문하면, 디렉터는 둘 중 몇 개가 참인지 알려준다.",
    "6-1": "머리뼈는 10보다 크고 60보다 작은 3의 배수 중 가장 큰 홀수이다.",
    "6-2": "몸통뼈는 8의 배수이며 6의 배수이다.",
    "6-3": "다리뼈는 13의 배수이다.",
    "6-4": "꼬리뼈는 5의 배수이며 8의 배수이다.",
    "6-5": "머리뼈와 꼬리뼈의 합은 전체 총합의 절반보다 17만큼 더 크다.",
    "6-6": "다리뼈를 제곱하면 1500과 1600 사이의 수이다.",
    "6-7": "머리뼈와 몸통뼈의 차이는 11의 배수이다.",
    "6-8": "네 부위의 뼈 개수를 오름차순으로 나열할 때, 인접한 부위 간의 차이는 각각 15, 1, 17이다.",
    "6-9": "머리뼈와 다리뼈를 합한 값의 일의 자리와 십의 자리의 합은 15이다.",
    "6-10": "꼬리뼈와 몸통뼈를 합한 값의 일의 자리와 십의 자리의 합은 10이다.",
    "6-11": "꼬리뼈를 다리뼈로 나누었을 때 몫은 1이다.",
    "6-12": "가장 개수가 많은 두 부위의 합은, 가장 개수가 적은 두 부위의 합보다 34만큼 더 크다.",
    "6-13": "몸통뼈의 일의 자리는 4이다.",
    "6-14": "모든 부위의 일의 자리 숫자를 합하면 20이다.",
    "6-15": "최종 감정권: 원하는 부위 하나를 골라 디렉터에게 정확한 개수의 '일의 자리'가 홀수인지 짝수인지 1회 질문할 수 있다.",
    "6-16": "최종 감정권: 원하는 부위 하나를 골라 디렉터에게 정확한 개수의 '십의 자리'가 짝수인지 홀수인지 1회 질문할 수 있다."
  }
}